Metadata-Version: 2.1
Name: alfa-utilities
Version: 0.2.2
Summary: ALFA utilities for base detectors
Home-page: https://github.com/SessionsOnceMore/alfa-utilities
Author: Tuan Anh Le
Author-email: tuananh.le@syrocon.de
License: MIT
Download-URL: https://github.com/SessionsOnceMore/alfa-utilities/archive/refs/tags/AlfaUtilities_v0.2.2.tar.gz
Platform: UNKNOWN
Classifier: Development Status :: 5 - Production/Stable
Classifier: Intended Audience :: Developers
Classifier: Topic :: Software Development :: Libraries :: Python Modules
Classifier: License :: OSI Approved :: MIT License
Classifier: Programming Language :: Python
Classifier: Programming Language :: Python :: 3
Classifier: Programming Language :: Python :: 3.8
Requires-Python: >=3.8
License-File: LICENSE.txt
